doh/__init__.py
doh/smartroom/__init__.py
doh/smartroom/deviceclient.py
smartroomdevice/__init__.py
smartroomdevice/deviceclient.py
doh_smartroom-0.0.3.dist-info/LICENSE
doh_smartroom-0.0.3.dist-info/METADATA
doh_smartroom-0.0.3.dist-info/WHEEL
doh_smartroom-0.0.3.dist-info/top_level.txt
doh_smartroom-0.0.3.dist-info/RECORD
