Metadata-Version: 2.1
Name: doh-smartroom
Version: 0.0.3
Summary: Device helper class for smartroom
Home-page: UNKNOWN
Author: Dominik Hofman
Author-email: dominikhofman@gmail.com
License: UNKNOWN
Platform: UNKNOWN
Classifier: Programming Language :: Python :: 3
Classifier: License :: OSI Approved :: MIT License
Classifier: Operating System :: OS Independent
